quantum_quarks-0.1.1.dist-info/METADATA
quantum_quarks-0.1.1.dist-info/WHEEL
quarks/__init__.py
quarks/main.py
quantum_quarks-0.1.1.dist-info/RECORD
